{
"type": "FeatureCollection",
"name": "RTPBCN",
"crs": { "type": "name", "properties": { "name": "urn:ogc:def:crs:OGC:1.3:CRS84" } },
"features": [
{ "type": "Feature", "properties": { "RCID": 5501, "PRIM": 1, "GRUP": 2, "OBJL": 103, "RVER": 1, "AGEN": 230, "FIDN": 887612, "FIDS": 1, "LNAM": "00E6000D8B3C0001", "CATRTB": 2, "RADWAL": "0.03-X,0.10-S", "SIGGRP": "(R)", "SCAMIN": 499999, "SORDAT": "20091204", "SORIND": "GB,GB,NMrpt,6646/09" }, "geometry": { "type": "Point", "coordinates": [ 105.9312122, -5.9012739 ] } }
]
}
